snapmanager/__init__.py
snapmanager/cli.py
snapmanager/core/manager.py
snapmanager/core/types.py
snapmanager/core/vss.py
snapmanager/utils/compute.py
snapmanager/utils/ui.py
snapmanager/utils/winrm.py
snapmanager-0.3.0.dist-info/LICENSE
snapmanager-0.3.0.dist-info/METADATA
snapmanager-0.3.0.dist-info/WHEEL
snapmanager-0.3.0.dist-info/entry_points.txt
snapmanager-0.3.0.dist-info/top_level.txt
snapmanager-0.3.0.dist-info/RECORD
