Metadata-Version: 2.2
Name: snapmanager
Version: 0.3.0
Summary: Makes VSS snapshot disks bootable in Google Cloud
Author: Ali Aktas
License: MIT License
Project-URL: Homepage, https://github.com/aliakts/snapmanager
Project-URL: Bug Tracker, https://github.com/aliakts/snapmanager/issues
Classifier: Programming Language :: Python :: 3
Classifier: License :: OSI Approved :: MIT License
Classifier: Operating System :: OS Independent
Requires-Python: >=3.8
License-File: LICENSE
Requires-Dist: google-cloud-compute>=1.23.0
Requires-Dist: rich>=10.0.0
Requires-Dist: pywinrm>=0.4.3
Dynamic: requires-python
